{
  "swagger": "2.0",
  "info": {
    "title": "Spanish Speaking Countries",
    "description": "Collection of Spanish Speaking Country Info",
    "version": "1.0.0"
  },
  "host": "localhost:8080",
  "basePath": "/",
  "schemes": [
    "http"
  ],
  "paths": {
    "/spanishSpeaking/": {
      "get": {
        "description": "",
        "responses": {
          "default": {
            "description": ""
          }
        }
      },
      "post": {
        "description": "",
        "responses": {
          "default": {
            "description": ""
          }
        }
      }
    },
    "/spanishSpeaking/{id}": {
      "get": {
        "description": "",
        "parameters": [
          {
            "name": "id",
            "in": "path",
            "required": true,
            "type": "string"
          }
        ],
        "responses": {
          "default": {
            "description": ""
          }
        }
      },
      "put": {
        "description": "",
        "parameters": [
          {
            "name": "id",
            "in": "path",
            "required": true,
            "type": "string"
          }
        ],
        "responses": {
          "default": {
            "description": ""
          }
        }
      },
      "delete": {
        "description": "",
        "parameters": [
          {
            "name": "id",
            "in": "path",
            "required": true,
            "type": "string"
          }
        ],
        "responses": {
          "default": {
            "description": ""
          }
        }
      }
    }
  }
}